nnst/__init__.py
nnst/downloader.py
nnst/nnst.py
nnst/nnst_utils/__init__.py
nnst/nnst_utils/params.py
nnst-0.0.0.5.dist-info/METADATA
nnst-0.0.0.5.dist-info/RECORD
nnst-0.0.0.5.dist-info/WHEEL
nnst-0.0.0.5.dist-info/top_level.txt
