Metadata-Version: 2.1
Name: nnst
Version: 0.0.0.5
Summary: Korean News Dataset For ML
Home-page: https://github.com/jason9693/NNST-Naver-News-for-Standard-and-Technology-Database
Author: Yang Kichang
Author-email: ykcha9@gmail.com
License: MIT
Download-URL: https://github.com/jason9693/NNST-Naver-News-for-Standard-and-Technology-Database/archive/0.0.1.tar.gz
Platform: UNKNOWN
Classifier: Development Status :: 4 - Beta
Classifier: Intended Audience :: Developers
Classifier: License :: OSI Approved :: MIT License
Classifier: Programming Language :: Python :: 3.6
Classifier: Programming Language :: Python :: 3.5
Classifier: Programming Language :: Python :: 3.4
Requires-Python: >=3
Requires-Dist: bs4 (>=0.0.1)
Requires-Dist: nose (>=1.3.7)
Requires-Dist: numpy (>=1.15.0)
Requires-Dist: pandas (>=0.23.4)
Requires-Dist: requests (>=2.19.1)
Requires-Dist: urllib3 (>=1.23)
